fopy/__init__.py
fopy/cli.py
fopy/fopy.py
fopy-0.0.0.dev1.dist-info/AUTHORS.rst
fopy-0.0.0.dev1.dist-info/LICENSE
fopy-0.0.0.dev1.dist-info/METADATA
fopy-0.0.0.dev1.dist-info/WHEEL
fopy-0.0.0.dev1.dist-info/entry_points.txt
fopy-0.0.0.dev1.dist-info/top_level.txt
fopy-0.0.0.dev1.dist-info/RECORD
