Metadata-Version: 2.1
Name: fopy
Version: 0.0.0.dev1
Summary: A Python package that makes working with math formulas convienant, powerfull and fast. 
Home-page: https://github.com/AzizAlqasem/fopy
Author: Abdulaziz Alqasem
Author-email: Aziz_Alqasem@hotmail.com
License: MIT license
Keywords: fopy
Platform: UNKNOWN
Classifier: Development Status :: 2 - Pre-Alpha
Classifier: Intended Audience :: Developers
Classifier: License :: OSI Approved :: MIT License
Classifier: Natural Language :: English
Classifier: Programming Language :: Python :: 3
Classifier: Programming Language :: Python :: 3.5
Classifier: Programming Language :: Python :: 3.6
Classifier: Programming Language :: Python :: 3.7
Classifier: Programming Language :: Python :: 3.8
Requires-Python: >=3.5
Requires-Dist: numpy (>=1.14.0)
Requires-Dist: sympy (>=1.5.0)
Requires-Dist: pandas (>=1.0.0)
Requires-Dist: Click (>=7.0)
